[
  {
    "Name": "Alex Johnson",
    "id": "#001",
    "OrderDate": "June 10, 2024",
    "CheckIn": "June 10, 2024",
    "CheckOut": "June 15, 2024",
    "SpecialRequest": "Late check-out at 2 PM",
    "RoomType": "Single Bed",
    "RoomNumber": "101",
    "Status": "Check In"
  },
  {
    "Name": "Ella Thompson",
    "id": "#002",
    "OrderDate": "June 11, 2024",
    "CheckIn": "June 11, 2024",
    "CheckOut": "June 16, 2024",
    "SpecialRequest": "Extra pillows",
    "RoomType": "Double Bed",
    "RoomNumber": "102",
    "Status": "In Progress"
  },
  {
    "Name": "Ryan Clark",
    "id": "#003",
    "OrderDate": "June 12, 2024",
    "CheckIn": "June 12, 2024",
    "CheckOut": "June 17, 2024",
    "SpecialRequest": "High floor room",
    "RoomType": "Double Superior",
    "RoomNumber": "103",
    "Status": "Check Out"
  },
  {
    "Name": "Olivia Roberts",
    "id": "#004",
    "OrderDate": "June 13, 2024",
    "CheckIn": "June 13, 2024",
    "CheckOut": "June 18, 2024",
    "SpecialRequest": "Vegetarian breakfast",
    "RoomType": "Suite",
    "RoomNumber": "104",
    "Status": "Check In"
  },
  {
    "Name": "Luke Harris",
    "id": "#005",
    "OrderDate": "June 14, 2024",
    "CheckIn": "June 14, 2024",
    "CheckOut": "June 19, 2024",
    "SpecialRequest": "Early check-in at 10 AM",
    "RoomType": "Single Bed",
    "RoomNumber": "105",
    "Status": "In Progress"
  },
  {
    "Name": "Sophia Walker",
    "id": "#006",
    "OrderDate": "June 15, 2024",
    "CheckIn": "June 15, 2024",
    "CheckOut": "June 20, 2024",
    "SpecialRequest": "Extra towels",
    "RoomType": "Double Bed",
    "RoomNumber": "106",
    "Status": "Check Out"
  },
  {
    "Name": "Noah King",
    "id": "#007",
    "OrderDate": "June 16, 2024",
    "CheckIn": "June 16, 2024",
    "CheckOut": "June 21, 2024",
    "SpecialRequest": "Non-smoking room",
    "RoomType": "Double Superior",
    "RoomNumber": "107",
    "Status": "Check In"
  },
  {
    "Name": "Mia Scott",
    "id": "#008",
    "OrderDate": "June 17, 2024",
    "CheckIn": "June 17, 2024",
    "CheckOut": "June 22, 2024",
    "SpecialRequest": "Late check-in at 11 PM",
    "RoomType": "Suite",
    "RoomNumber": "108",
    "Status": "In Progress"
  },
  {
    "Name": "Jack Baker",
    "id": "#009",
    "OrderDate": "June 18, 2024",
    "CheckIn": "June 18, 2024",
    "CheckOut": "June 23, 2024",
    "SpecialRequest": "Sea view room",
    "RoomType": "Single Bed",
    "RoomNumber": "109",
    "Status": "Check Out"
  },
  {
    "Name": "Ava Green",
    "id": "#010",
    "OrderDate": "June 19, 2024",
    "CheckIn": "June 19, 2024",
    "CheckOut": "June 24, 2024",
    "SpecialRequest": "King-sized bed",
    "RoomType": "Double Bed",
    "RoomNumber": "110",
    "Status": "Check In"
  }
]
